mlnotes/__init__.py
mlnotes/__main__.py
mlnotes/mlnotes.py
mlnotes-0.0.2.dist-info/LICENSE
mlnotes-0.0.2.dist-info/METADATA
mlnotes-0.0.2.dist-info/WHEEL
mlnotes-0.0.2.dist-info/top_level.txt
mlnotes-0.0.2.dist-info/RECORD
