Metadata-Version: 2.1
Name: mlnotes
Version: 0.0.2
Summary: Save information of your ml projects
Home-page: https://github.com/pypa/sampleproject
Author: Satyam Mishra
Author-email: tubex998@gmail.com
Project-URL: Bug Tracker, https://github.com/pypa/sampleproject/issues
Classifier: Programming Language :: Python :: 3
Classifier: License :: OSI Approved :: MIT License
Classifier: Operating System :: OS Independent
Requires-Python: >=3.6
License-File: LICENSE
